[{"inputs": [], "name": "AdlNotEnabled", "type": "error"}, {"inputs": [{"internalType": "address", "name": "market", "type": "address"}], "name": "DisabledMarket", "type": "error"}, {"inputs": [], "name": "EmptyMarket", "type": "error"}, {"inputs": [{"internalType": "uint256", "name": "sizeDeltaUsd", "type": "uint256"}, {"internalType": "uint256", "name": "positionSizeInUsd", "type": "uint256"}], "name": "InvalidSizeDeltaForAdl", "type": "error"}, {"inputs": [{"internalType": "uint256", "name": "minOracleTimestamp", "type": "uint256"}, {"internalType": "uint256", "name": "expectedTimestamp", "type": "uint256"}], "name": "OracleTimestampsAreSmallerThanRequired", "type": "error"}, {"inputs": [{"internalType": "contract DataStore", "name": "dataStore", "type": "DataStore"}, {"internalType": "contract Oracle", "name": "oracle", "type": "Oracle"}, {"internalType": "address", "name": "market", "type": "address"}, {"internalType": "bool", "name": "isLong", "type": "bool"}], "name": "validateAdl", "outputs": [], "stateMutability": "view", "type": "function"}]